{"division":"\uC639\uAE30\uC7A5\uC774","videos":[{"id":"okIy30EmJDY","title":"\uAC70\uB8E9 \uAC70\uB8E9 \uAC70\uB8E9 by \uD638\uC0B0\uB098\uC2F1\uC5B4\uC988","link":"https://youtu.be/okIy30EmJDY","date":"2020-04-14 16:44:14"},{"id":"t83MXF_NigA","title":"\uB0B4 \uC601\uD63C\uC774 \uC740\uCD1D \uC785\uC5B4","link":"https://youtu.be/t83MXF_NigA","date":"2020-04-14 16:44:13"},{"id":"D7m5cWPc4Po","title":"\uC8FC\uC640 \uAC19\uC774 \uAE38 \uAC00\uB294 \uAC83 (\uC544\uCE74\uD3A0\uB77C)","link":"https://youtu.be/D7m5cWPc4Po","date":"2020-04-14 16:44:13"},{"id":"b8MHkczceC4","title":"\uAC15\uBB3C\uAC19\uC774 \uD750\uB974\uB294 \uAE30\uC068","link":"https://youtu.be/b8MHkczceC4","date":"2020-04-14 16:44:13"},{"id":"Nt5AueBWlIo","title":"\uB098\uB97C \uD5A5\uD55C \uC8FC\uC758 \uC0AC\uB791 by \uC639\uAE30\uC7A5\uC774","link":"https://youtu.be/Nt5AueBWlIo","date":"2020-04-14 16:44:13"},{"id":"_JGvCitA39o","title":"\uC2ED\uC790\uAC00\uB85C \uAC11\uB2C8\uB2E4 by \uD638\uC0B0\uB098\uC2F1\uC5B4\uC988(with \uD55C\uC6C5\uC7AC)","link":"https://youtu.be/_JGvCitA39o","date":"2020-04-14 16:44:13"},{"id":"8HyIAnV-yDY","title":"\uB0B4 \uB9D8\uC758 \uC8FC\uC5EC \uC18C\uB9DD\uB418\uC18C\uC11C (\uC544\uCE74\uD3A0\uB77C)","link":"https://youtu.be/8HyIAnV-yDY","date":"2020-04-14 16:44:13"},{"id":"ri8vwr3ps8k","title":"\uB098 \uAC19\uC740 \uC8C4\uC778 \uC0B4\uB9AC\uC2E0","link":"https://youtu.be/ri8vwr3ps8k","date":"2020-04-14 16:44:13"},{"id":"4KGHG8tfbPw","title":"\uC9C0\uAE08\uC740 \uC5D8\uB9AC\uC57C \uB54C\uCC98\uB7FC (Days Of Elijah)","link":"https://youtu.be/4KGHG8tfbPw","date":"2020-04-14 16:44:13"},{"id":"JanAdHABo20","title":"\uB0B4 \uAD6C\uC8FC \uC608\uC218\uB97C \uB354\uC6B1 \uC0AC\uB791","link":"https://youtu.be/JanAdHABo20","date":"2020-04-14 16:44:13"},{"id":"NhSFMe46Kb4","title":"\uB0B4 \uC774\uB984 \uC544\uC2DC\uC8E0 by \uC639\uAE30\uC7A5\uC774","link":"https://youtu.be/NhSFMe46Kb4","date":"2020-04-14 16:44:13"},{"id":"Z60jbvQMmoU","title":"\uB098 \uBB34\uC5C7\uACFC\uB3C4 \uC8FC\uB2D8\uC744 by \uC639\uAE30\uC7A5\uC774","link":"https://youtu.be/Z60jbvQMmoU","date":"2020-04-14 16:44:13"},{"id":"-1XhN5M0KbM","title":"\uC8FC\uAED8 \uAC00\uC624\uB2C8","link":"https://youtu.be/-1XhN5M0KbM","date":"2020-04-14 16:44:13"}],"total_count":13}