{"division":"\uD788\uC988\uC70C","videos":[{"id":"c7-gf0Xlvwk","title":"\uD788\uC988\uC70C 7\uC9D1 Part 1 \uC218\uB85D\uACE1 '\uC608\uC218\uB85C \uC0B4\uAE30 \uC6D0\uD574'","link":"https://youtu.be/c7-gf0Xlvwk","date":"2022-12-21 09:43:37"},{"id":"LRf-gEjGedU","title":"\uD788\uC988\uC70C 7\uC9D1 Part 1 \uC218\uB85D\uACE1 '\uB354\uC6B1 \uC784\uD558\uC18C\uC11C'","link":"https://youtu.be/LRf-gEjGedU","date":"2022-12-21 09:43:37"},{"id":"apMiU-rX-5I","title":"\uD788\uC988\uC70C 7\uC9D1 Part 2 \uC218\uB85D\uACE1 '\uC2ED\uC790\uAC00'","link":"https://youtu.be/apMiU-rX-5I","date":"2022-12-21 09:43:37"},{"id":"VXtdNHspT5o","title":"\uD788\uC988\uC70C 7\uC9D1 Part 2 \uC218\uB85D\uACE1 '\uADF8\uC800 \uC0AC\uB791\uB9CC \uD558\uBA70'","link":"https://youtu.be/VXtdNHspT5o","date":"2022-12-21 09:43:37"},{"id":"zr2eUUUzt-g","title":"\uD788\uC988\uC70C 7\uC9D1 Part 2 \uC218\uB85D\uACE1 '\uC2ED\uC790\uAC00' MR","link":"https://youtu.be/zr2eUUUzt-g","date":"2022-12-21 09:43:37"},{"id":"vyNatQw06w8","title":"\uD788\uC988\uC70C 3\uC9D1 \uC218\uB85D\uACE1 '\uAD11\uC57C\uB97C \uC9C0\uB098\uBA70' MR","link":"https://youtu.be/vyNatQw06w8","date":"2022-12-21 09:43:37"},{"id":"-PQt02RFj30","title":"\uD788\uC988\uC70C6\uC9D1 \uC218\uB85D\uACE1 '\uADF8\uB300\uB97C \uC0AC\uB791\uD558\uAE30\uB97C' MR","link":"https://youtu.be/-PQt02RFj30","date":"2022-12-21 09:43:37"},{"id":"mbni--pc9bA","title":"\uD788\uC988\uC70C 2\uC9D1 \uC218\uB85D\uACE1 '\uC0AC\uB791' MR","link":"https://youtu.be/mbni--pc9bA","date":"2022-12-21 09:43:37"},{"id":"xlGTXAQFmfk","title":"\uD788\uC988\uC70C \uC131\uD0C4\uCC2C\uC591 7\uACE1 \uBAA8\uC74C","link":"https://youtu.be/xlGTXAQFmfk","date":"2022-12-21 09:43:37"},{"id":"nmq9cOK-mIQ","title":"\uD788\uC988\uC70C Piano & Violin \uC804\uACE1\uB4E3\uAE30 (62\uBD84)","link":"https://youtu.be/nmq9cOK-mIQ","date":"2022-12-21 09:43:37"},{"id":"Ziacc6K59Cs","title":"\uD788\uC988\uC70C HisWill 1\uC9D1 'Driven by Hiswill' \uC804\uACE1\uB4E3\uAE30 (55\uBD84)","link":"https://youtu.be/Ziacc6K59Cs","date":"2022-12-21 09:43:37"},{"id":"mtBJr0eIias","title":"\uD788\uC988\uC70C HisWill 2\uC9D1 'Healing by Hiswill' \uC804\uACE1\uB4E3\uAE30 (44\uBD84)","link":"https://youtu.be/mtBJr0eIias","date":"2022-12-21 09:43:37"},{"id":"qzYCJgDlBug","title":"\uD788\uC988\uC70C HisWill 3\uC9D1 '\uC0B4\uC544\uAC00\uB2E4' \uC804\uACE1\uB4E3\uAE30 (44\uBD84)","link":"https://youtu.be/qzYCJgDlBug","date":"2022-12-21 09:43:37"},{"id":"Wmpv_By-MSM","title":"\uD788\uC988\uC70C HisWill 4\uC9D1 '\uC120\uBB3C' \uC804\uACE1\uB4E3\uAE30 (44\uBD84)","link":"https://youtu.be/Wmpv_By-MSM","date":"2022-12-21 09:43:37"},{"id":"ud5to8NJeN4","title":"\uD788\uC988\uC70C HisWill 5\uC9D1 '\uBBFF\uC74C\uC774 \uD544\uC694\uD574' \uC804\uACE1\uB4E3\uAE30 (40\uBD84)","link":"https://youtu.be/ud5to8NJeN4","date":"2022-12-21 09:43:37"},{"id":"8YlIpDjMmdo","title":"\uD788\uC988\uC70C HisWill 6\uC9D1 'STOP' \uC804\uACE1\uB4E3\uAE30 (43\uBD84)","link":"https://youtu.be/8YlIpDjMmdo","date":"2022-12-21 09:43:37"},{"id":"MyFxvx81JZE","title":"\uD788\uC988\uC70C HisWill 7\uC9D1 Part 1+2 \uC804\uACE1\uB4E3\uAE30 (46\uBD84)","link":"https://youtu.be/MyFxvx81JZE","date":"2022-12-21 09:43:37"},{"id":"fRiPmf3UR1U","title":"\uD788\uC988\uC70C \uBCA0\uC2A4\uD2B8 \uCC2C\uC591","link":"https://youtu.be/fRiPmf3UR1U","date":"2022-12-21 09:43:37"}],"total_count":18}